odoo/addons/loyalty_criteria_multi_product/README.rst
odoo/addons/loyalty_criteria_multi_product/__init__.py
odoo/addons/loyalty_criteria_multi_product/__manifest__.py
odoo/addons/loyalty_criteria_multi_product/i18n/coupon_criteria_multi_product.pot
odoo/addons/loyalty_criteria_multi_product/i18n/es.po
odoo/addons/loyalty_criteria_multi_product/i18n/it.po
odoo/addons/loyalty_criteria_multi_product/i18n/loyalty_criteria_multi_product.pot
odoo/addons/loyalty_criteria_multi_product/models/__init__.py
odoo/addons/loyalty_criteria_multi_product/models/loyalty_criteria.py
odoo/addons/loyalty_criteria_multi_product/models/loyalty_program.py
odoo/addons/loyalty_criteria_multi_product/models/loyalty_rule.py
odoo/addons/loyalty_criteria_multi_product/readme/CONFIGURE.md
odoo/addons/loyalty_criteria_multi_product/readme/CONTEXT.md
odoo/addons/loyalty_criteria_multi_product/readme/CONTRIBUTORS.md
odoo/addons/loyalty_criteria_multi_product/readme/DESCRIPTION.md
odoo/addons/loyalty_criteria_multi_product/security/ir.model.access.csv
odoo/addons/loyalty_criteria_multi_product/static/description/icon.png
odoo/addons/loyalty_criteria_multi_product/static/description/icon.svg
odoo/addons/loyalty_criteria_multi_product/static/description/index.html
odoo/addons/loyalty_criteria_multi_product/tests/__init__.py
odoo/addons/loyalty_criteria_multi_product/tests/test_loyalty_criteria_multi_product.py
odoo/addons/loyalty_criteria_multi_product/views/loyalty_program_views.xml
odoo/addons/loyalty_criteria_multi_product/views/loyalty_rule_views.xml
odoo_addon_loyalty_criteria_multi_product-18.0.1.0.0.2.dist-info/METADATA
odoo_addon_loyalty_criteria_multi_product-18.0.1.0.0.2.dist-info/WHEEL
odoo_addon_loyalty_criteria_multi_product-18.0.1.0.0.2.dist-info/top_level.txt
odoo_addon_loyalty_criteria_multi_product-18.0.1.0.0.2.dist-info/RECORD
